{
  "$schema": "https://developer.microsoft.com/json-schemas/fabric/item/report/definition/visualContainer/2.1.0/schema.json",
  "name": "172f718142f84db612a6",
  "position": {
    "x": 62.666666666666664,
    "y": 68.666666666666671,
    "z": 6000,
    "height": 132.66666666666666,
    "width": 402,
    "tabOrder": 6000
  },
  "visual": {
    "visualType": "tableEx",
    "query": {
      "queryState": {
        "Values": {
          "projections": [
            {
              "field": {
                "Column": {
                  "Expression": {
                    "SourceRef": {
                      "Entity": "Org"
                    }
                  },
                  "Property": "Mission"
                }
              },
              "queryRef": "Org.Mission",
              "nativeQueryRef": "Mission"
            }
          ]
        }
      },
      "sortDefinition": {
        "sort": [
          {
            "field": {
              "Column": {
                "Expression": {
                  "SourceRef": {
                    "Entity": "Org"
                  }
                },
                "Property": "Mission"
              }
            },
            "direction": "Ascending"
          }
        ]
      }
    },
    "objects": {
      "columnWidth": [
        {
          "properties": {
            "value": {
              "expr": {
                "Literal": {
                  "Value": "314.71217274160654D"
                }
              }
            }
          },
          "selector": {
            "metadata": "Org.Mission"
          }
        }
      ],
      "values": [
        {
          "properties": {
            "wordWrap": {
              "expr": {
                "Literal": {
                  "Value": "true"
                }
              }
            }
          }
        }
      ]
    },
    "visualContainerObjects": {
      "stylePreset": [
        {
          "properties": {
            "name": {
              "expr": {
                "Literal": {
                  "Value": "'None'"
                }
              }
            }
          }
        }
      ],
      "background": [
        {
          "properties": {
            "show": {
              "expr": {
                "Literal": {
                  "Value": "true"
                }
              }
            }
          }
        }
      ],
      "visualHeader": [
        {
          "properties": {
            "show": {
              "expr": {
                "Literal": {
                  "Value": "false"
                }
              }
            }
          }
        }
      ]
    }
  }
}