{
  "$schema": "https://developer.microsoft.com/json-schemas/fabric/item/report/definition/visualContainer/2.1.0/schema.json",
  "name": "ff0637c3394ed0aac91b",
  "position": {
    "x": 296.4682341170585,
    "y": 10.885442721360681,
    "z": 7000,
    "height": 474.47723861930962,
    "width": 475.1175587793897,
    "tabOrder": 6000
  },
  "visual": {
    "visualType": "columnChart",
    "query": {
      "queryState": {
        "Category": {
          "projections": [
            {
              "field": {
                "Column": {
                  "Expression": {
                    "SourceRef": {
                      "Entity": "020_ActivitiesSplit"
                    }
                  },
                  "Property": "Activities AI - Level.1"
                }
              },
              "queryRef": "020_ActivitiesSplit.Activities AI - Level.1",
              "nativeQueryRef": "Activities AI - Level.1",
              "active": true
            },
            {
              "field": {
                "Column": {
                  "Expression": {
                    "SourceRef": {
                      "Entity": "020_ActivitiesSplit"
                    }
                  },
                  "Property": "Activities AI - Level.2"
                }
              },
              "queryRef": "020_ActivitiesSplit.Activities AI - Level.2",
              "nativeQueryRef": "Activities AI - Level.2",
              "active": false
            },
            {
              "field": {
                "Column": {
                  "Expression": {
                    "SourceRef": {
                      "Entity": "020_ActivitiesSplit"
                    }
                  },
                  "Property": "Activities AI - Level.3"
                }
              },
              "queryRef": "020_ActivitiesSplit.Activities AI - Level.3",
              "nativeQueryRef": "Activities AI - Level.3",
              "active": false
            }
          ]
        },
        "Series": {
          "projections": [
            {
              "field": {
                "Column": {
                  "Expression": {
                    "SourceRef": {
                      "Entity": "020_ActivitiesSplit"
                    }
                  },
                  "Property": "Activities AI - Level.1"
                }
              },
              "queryRef": "020_ActivitiesSplit.Activities AI - Level.1",
              "nativeQueryRef": "Activities AI - Level.1"
            }
          ]
        },
        "Y": {
          "projections": [
            {
              "field": {
                "Aggregation": {
                  "Expression": {
                    "Column": {
                      "Expression": {
                        "SourceRef": {
                          "Entity": "020_ActivitiesSplit"
                        }
                      },
                      "Property": "Activities AI - Level.1"
                    }
                  },
                  "Function": 5
                }
              },
              "queryRef": "CountNonNull(020_ActivitiesSplit.Activities AI - Level.1)",
              "nativeQueryRef": "Count of Activities AI - Level.1"
            }
          ]
        }
      },
      "sortDefinition": {
        "sort": [
          {
            "field": {
              "Aggregation": {
                "Expression": {
                  "Column": {
                    "Expression": {
                      "SourceRef": {
                        "Entity": "020_ActivitiesSplit"
                      }
                    },
                    "Property": "Activities AI - Level.1"
                  }
                },
                "Function": 5
              }
            },
            "direction": "Descending"
          }
        ]
      }
    },
    "visualContainerObjects": {
      "title": [
        {
          "properties": {
            "text": {
              "expr": {
                "Literal": {
                  "Value": "'Right click to drill into any level!'"
                }
              }
            }
          }
        }
      ]
    }
  },
  "filterConfig": {
    "filters": [
      {
        "name": "04b87601580d098196bc",
        "field": {
          "Column": {
            "Expression": {
              "SourceRef": {
                "Entity": "020_ActivitiesSplit"
              }
            },
            "Property": "Activities AI - Level.1"
          }
        },
        "type": "Categorical",
        "filter": {
          "Version": 2,
          "From": [
            {
              "Name": "0",
              "Entity": "020_ActivitiesSplit",
              "Type": 0
            }
          ],
          "Where": [
            {
              "Condition": {
                "Not": {
                  "Expression": {
                    "In": {
                      "Expressions": [
                        {
                          "Column": {
                            "Expression": {
                              "SourceRef": {
                                "Source": "0"
                              }
                            },
                            "Property": "Activities AI - Level.1"
                          }
                        }
                      ],
                      "Values": [
                        [
                          {
                            "Literal": {
                              "Value": "''"
                            }
                          }
                        ],
                        [
                          {
                            "Literal": {
                              "Value": "'No specific AI focus'"
                            }
                          }
                        ],
                        [
                          {
                            "Literal": {
                              "Value": "'Government'"
                            }
                          }
                        ]
                      ]
                    }
                  }
                }
              }
            }
          ]
        },
        "objects": {
          "general": [
            {
              "properties": {
                "isInvertedSelectionMode": {
                  "expr": {
                    "Literal": {
                      "Value": "true"
                    }
                  }
                }
              }
            }
          ]
        }
      }
    ]
  }
}